frontend/bun.lock
frontend/components.json
frontend/index.html
frontend/package.json
frontend/tsconfig.json
frontend/vite.config.js
frontend/public/favicon.ico
frontend/public/logo192.png
frontend/public/logo512.png
frontend/public/manifest.json
frontend/public/robots.txt
frontend/src/main.tsx
frontend/src/reportWebVitals.ts
frontend/src/routeTree.gen.ts
frontend/src/styles.css
frontend/src/components/Header.tsx
frontend/src/components/ui/button.tsx
frontend/src/lib/utils.ts
frontend/src/routes/__root.tsx
frontend/src/routes/details.$pair.tsx
frontend/src/routes/index.tsx
frontend/src/routes/similarity-matrix.tsx
modelith/__init__.py
modelith/cli/app.py
modelith/cli/commands/evaluate.py
modelith/cli/commands/extract.py
modelith/cli/commands/init.py
modelith/cli/commands/kaggle_dump.py
modelith/cli/commands/classes/__init__.py
modelith/cli/commands/classes/create.py
modelith/cli/commands/classes/group.py
modelith/cli/commands/classes/upload.py
modelith/core/ast_comparison.py
modelith/core/folder_hash.py
modelith/core/notebook_analyzer.py
modelith/core/sanitize_filenames.py
modelith/core/utils.py
modelith/core/db/db_classes.py
modelith/core/db/db_operations.py
modelith/core/db/generate_database.py
modelith/core/db/single-row.json
modelith/kaggle_automation/kaggle_login.py
modelith-0.2.0.dist-info/METADATA
modelith-0.2.0.dist-info/WHEEL
modelith-0.2.0.dist-info/entry_points.txt
modelith-0.2.0.dist-info/licenses/LICENSE
modelith-0.2.0.dist-info/RECORD
