Metadata-Version: 2.4
Name: modelith
Version: 0.2.0
Summary: Evaluate your student's code
Project-URL: Repository, https://github.com/pranavtechie/modelith
Project-URL: Homepage, https://modelith.com
Author-email: Pranav Mandava <pranav.techiegeek@gmail.com>
License-Expression: MIT
License-File: LICENSE
Classifier: Development Status :: 4 - Beta
Classifier: Intended Audience :: Developers
Classifier: License :: OSI Approved :: MIT License
Classifier: Operating System :: OS Independent
Classifier: Programming Language :: Python
Classifier: Programming Language :: Python :: 3
Classifier: Programming Language :: Python :: 3.11
Classifier: Typing :: Typed
Requires-Python: <3.12,>=3.11
Requires-Dist: jupyter-notebook-parser>=0.1.4
Requires-Dist: matplotlib>=3.10.1
Requires-Dist: pandas>=2.2.3
Requires-Dist: platformdirs>=4.3.7
Requires-Dist: playwright>=1.51.0
Requires-Dist: python-dotenv>=1.1.0
Requires-Dist: requests>=2.32.3
Requires-Dist: rich>=13.9.4
Requires-Dist: sqlalchemy>=2.0.40
Requires-Dist: typer>=0.15.2
